fixture_foundry/__init__.py
fixture_foundry/context.py
fixture_foundry/fixtures.py
fixture_foundry/pytest_plugin.py
fixture_foundry/utils.py
fixture_foundry-0.2.4.dist-info/METADATA
fixture_foundry-0.2.4.dist-info/WHEEL
fixture_foundry-0.2.4.dist-info/licenses/LICENSE
fixture_foundry-0.2.4.dist-info/RECORD
