Metadata-Version: 2.4
Name: fixture-foundry
Version: 0.2.4
Summary: Fixtures and helpers to create AWS infrastructure (via LocalStack) and containerized databases locally for fast, reproducible integration testing.
Project-URL: Homepage, https://github.com/DanRepik/fixture_foundry
Project-URL: Repository, https://github.com/DanRepik/fixture_foundry
Project-URL: Issues, https://github.com/DanRepik/fixture_foundry/issues
Author-email: Dan Repik <dan.repik@example.com>
License-Expression: MIT
License-File: LICENSE
Keywords: fixtures,python,test-data,testing
Classifier: Development Status :: 3 - Alpha
Classifier: Intended Audience :: Developers
Classifier: Operating System :: OS Independent
Classifier: Programming Language :: Python :: 3
Classifier: Programming Language :: Python :: 3.8
Classifier: Programming Language :: Python :: 3.9
Classifier: Programming Language :: Python :: 3.10
Classifier: Programming Language :: Python :: 3.11
Classifier: Programming Language :: Python :: 3.12
Classifier: Topic :: Software Development :: Libraries :: Python Modules
Classifier: Topic :: Software Development :: Testing
Requires-Python: >=3.8
Provides-Extra: dev
Requires-Dist: black>=23.0.0; extra == 'dev'
Requires-Dist: docker>=7.1.0; extra == 'dev'
Requires-Dist: flake8>=6.0.0; extra == 'dev'
Requires-Dist: hatch>=1.18.0; extra == 'dev'
Requires-Dist: isort>=5.12.0; extra == 'dev'
Requires-Dist: mypy>=1.0.0; extra == 'dev'
Requires-Dist: psycopg2-binary>=2.9.10; extra == 'dev'
Requires-Dist: pulumi>=3.198.0; extra == 'dev'
Requires-Dist: pytest-cov>=4.0.0; extra == 'dev'
Requires-Dist: pytest>=7.0.0; extra == 'dev'
Requires-Dist: requests>=2.32.5; extra == 'dev'
Provides-Extra: docs
Requires-Dist: sphinx-rtd-theme>=1.2.0; extra == 'docs'
Requires-Dist: sphinx>=5.0.0; extra == 'docs'
